telnetlib_external_socket.py
telnetlib_external_socket-1.0.dist-info/METADATA
telnetlib_external_socket-1.0.dist-info/WHEEL
telnetlib_external_socket-1.0.dist-info/top_level.txt
telnetlib_external_socket-1.0.dist-info/RECORD
